<?xml version="1.0" encoding="UTF-8"?>
<CreditNote xmlns="urn:oasis:names:specification:ubl:schema:xsd:CreditNote-2"
            xmlns:cac="urn:oasis:names:specification:ubl:schema:xsd:CommonAggregateComponents-2"
            xmlns:cbc="urn:oasis:names:specification:ubl:schema:xsd:CommonBasicComponents-2">
  <cbc:CustomizationID>urn:cen.eu:en16931:2017#compliant#urn:fdc:peppol.eu:2017:poacc:billing:3.0</cbc:CustomizationID>
  <cbc:ProfileID>urn:fdc:peppol.eu:2017:poacc:billing:01:1.0</cbc:ProfileID>
  <cbc:ID>CN-2024-0007</cbc:ID>
  <cbc:IssueDate>2024-05-10</cbc:IssueDate>
  <cbc:CreditNoteTypeCode>381</cbc:CreditNoteTypeCode>
  <cbc:Note>Credit for returned goods on invoice INV-2024-0042.</cbc:Note>
  <cbc:DocumentCurrencyCode>EUR</cbc:DocumentCurrencyCode>
  <cbc:BuyerReference>PO-558</cbc:BuyerReference>
  <cac:BillingReference>
    <cac:InvoiceDocumentReference>
      <cbc:ID>INV-2024-0042</cbc:ID>
      <cbc:IssueDate>2024-05-02</cbc:IssueDate>
    </cac:InvoiceDocumentReference>
  </cac:BillingReference>
  <cac:AccountingSupplierParty>
    <cac:Party>
      <cbc:EndpointID schemeID="0192">983294337</cbc:EndpointID>
      <cac:PartyName>
        <cbc:Name>Café Søyland AS</cbc:Name>
      </cac:PartyName>
      <cac:PostalAddress>
        <cbc:StreetName>Storgata 12</cbc:StreetName>
        <cbc:CityName>Oslo</cbc:CityName>
        <cbc:PostalZone>0155</cbc:PostalZone>
        <cac:Country>
          <cbc:IdentificationCode>NO</cbc:IdentificationCode>
        </cac:Country>
      </cac:PostalAddress>
      <cac:PartyLegalEntity>
        <cbc:RegistrationName>Café Søyland AS</cbc:RegistrationName>
        <cbc:CompanyID schemeID="0192">983294337</cbc:CompanyID>
      </cac:PartyLegalEntity>
    </cac:Party>
  </cac:AccountingSupplierParty>
  <cac:AccountingCustomerParty>
    <cac:Party>
      <cbc:EndpointID schemeID="0192">311669675</cbc:EndpointID>
      <cac:PartyName>
        <cbc:Name>Nordlys Konsult AS</cbc:Name>
      </cac:PartyName>
      <cac:PostalAddress>
        <cbc:StreetName>Kongens gate 4</cbc:StreetName>
        <cbc:CityName>Bergen</cbc:CityName>
        <cbc:PostalZone>5003</cbc:PostalZone>
        <cac:Country>
          <cbc:IdentificationCode>NO</cbc:IdentificationCode>
        </cac:Country>
      </cac:PostalAddress>
      <cac:PartyLegalEntity>
        <cbc:RegistrationName>Nordlys Konsult AS</cbc:RegistrationName>
        <cbc:CompanyID schemeID="0192">311669675</cbc:CompanyID>
      </cac:PartyLegalEntity>
    </cac:Party>
  </cac:AccountingCustomerParty>
  <cac:TaxTotal>
    <cbc:TaxAmount currencyID="EUR">25.00</cbc:TaxAmount>
    <cac:TaxSubtotal>
      <cbc:TaxableAmount currencyID="EUR">100.00</cbc:TaxableAmount>
      <cbc:TaxAmount currencyID="EUR">25.00</cbc:TaxAmount>
      <cac:TaxCategory>
        <cbc:ID>S</cbc:ID>
        <cbc:Percent>25.0</cbc:Percent>
        <cac:TaxScheme>
          <cbc:ID>VAT</cbc:ID>
        </cac:TaxScheme>
      </cac:TaxCategory>
    </cac:TaxSubtotal>
  </cac:TaxTotal>
  <cac:LegalMonetaryTotal>
    <cbc:LineExtensionAmount currencyID="EUR">100.00</cbc:LineExtensionAmount>
    <cbc:TaxExclusiveAmount currencyID="EUR">100.00</cbc:TaxExclusiveAmount>
    <cbc:TaxInclusiveAmount currencyID="EUR">125.00</cbc:TaxInclusiveAmount>
    <cbc:PayableAmount currencyID="EUR">125.00</cbc:PayableAmount>
  </cac:LegalMonetaryTotal>
  <cac:CreditNoteLine>
    <cbc:ID>1</cbc:ID>
    <cbc:CreditedQuantity unitCode="C62">2</cbc:CreditedQuantity>
    <cbc:LineExtensionAmount currencyID="EUR">100.00</cbc:LineExtensionAmount>
    <cac:Item>
      <cbc:Name>Espresso blend, 1kg bag (returned)</cbc:Name>
      <cac:ClassifiedTaxCategory>
        <cbc:ID>S</cbc:ID>
        <cbc:Percent>25.0</cbc:Percent>
        <cac:TaxScheme>
          <cbc:ID>VAT</cbc:ID>
        </cac:TaxScheme>
      </cac:ClassifiedTaxCategory>
    </cac:Item>
    <cac:Price>
      <cbc:PriceAmount currencyID="EUR">50.00</cbc:PriceAmount>
    </cac:Price>
  </cac:CreditNoteLine>
</CreditNote>
